README.txt
setup.py
aws/__init__.py
aws.zope2zcmldoc.egg-info/PKG-INFO
aws.zope2zcmldoc.egg-info/SOURCES.txt
aws.zope2zcmldoc.egg-info/dependency_links.txt
aws.zope2zcmldoc.egg-info/entry_points.txt
aws.zope2zcmldoc.egg-info/namespace_packages.txt
aws.zope2zcmldoc.egg-info/not-zip-safe
aws.zope2zcmldoc.egg-info/requires.txt
aws.zope2zcmldoc.egg-info/top_level.txt
aws/zope2zcmldoc/__init__.py
aws/zope2zcmldoc/browser.py
aws/zope2zcmldoc/config.py
aws/zope2zcmldoc/configure.zcml
aws/zope2zcmldoc/controlpanel.py
aws/zope2zcmldoc/interfaces.py
aws/zope2zcmldoc/tests.py
aws/zope2zcmldoc/utils.py
aws/zope2zcmldoc/version.txt
aws/zope2zcmldoc/zmi/aws-zope2zcmldoc-icon.gif
aws/zope2zcmldoc/zmi/controlpanel_macros.pt
aws/zope2zcmldoc/zmi/manage_main.pt
aws/zope2zcmldoc/zmi/view_directive.pt
aws/zope2zcmldoc/zmi/view_namespace.pt
aws/zope2zcmldoc/zmi/view_subdirective.pt
docs/HISTORY.txt