Metadata-Version: 1.0
Name: aws.zope2zcmldoc
Version: 1.0.0
Summary: ZCML documentation browser for Zope 2
Home-page: http://pypi.python.org/pypi/aws.zope2zcmldoc
Author: Gilles lenfant
Author-email: gilles.lenfant@alterway.fr
License: GPL
Keywords: zope2 zcml documentation
Platform: UNKNOWN
Classifier: Programming Language :: Python
Classifier: Framework :: Zope2
Classifier: Intended Audience :: Developers
Classifier: Development Status :: 5 - Production/Stable
Classifier: License :: OSI Approved :: GNU General Public License (GPL)
Classifier: Topic :: Software Development :: Documentation
